headless_coder_sdk/claude_agent_sdk/__init__.py
headless_coder_sdk/claude_agent_sdk/adapter.py
headless_coder_sdk_claude_agent-0.1.0.dist-info/METADATA
headless_coder_sdk_claude_agent-0.1.0.dist-info/WHEEL
headless_coder_sdk_claude_agent-0.1.0.dist-info/licenses/LICENSE
headless_coder_sdk_claude_agent-0.1.0.dist-info/RECORD
